seldon/__init__.py
seldon/anomaly_wrapper.py
seldon/fileutil.py
seldon/keras.py
seldon/sklearn_estimator.py
seldon/tensorflow_wrapper.py
seldon/util.py
seldon/vw.py
seldon/xgb.py
seldon/anomaly/AnomalyDetection.py
seldon/anomaly/__init__.py
seldon/cli/__init__.py
seldon/cli/attr_schema_utils.py
seldon/cli/cli_main.py
seldon/cli/cmd_alg.py
seldon/cli/cmd_api.py
seldon/cli/cmd_attr.py
seldon/cli/cmd_client.py
seldon/cli/cmd_db.py
seldon/cli/cmd_import.py
seldon/cli/cmd_keys.py
seldon/cli/cmd_memcached.py
seldon/cli/cmd_model.py
seldon/cli/cmd_pred.py
seldon/cli/cmd_rec_exp.py
seldon/cli/cmd_rpc.py
seldon/cli/db_utils.py
seldon/cli/import_actions_utils.py
seldon/cli/import_items_utils.py
seldon/cli/import_users_utils.py
seldon/cli/seldon_utils.py
seldon/cli/spark_utils.py
seldon/cli/zk_utils.py
seldon/cli/dbschema/mysql/api.sql
seldon/cli/dbschema/mysql/client.sql
seldon/cli/grafana/client-dashboard.json
seldon/luigi/__init__.py
seldon/luigi/spark.py
seldon/microservice/__init__.py
seldon/microservice/extension.py
seldon/microservice/microservice.py
seldon/microservice/predict.py
seldon/microservice/recommend.py
seldon/microservice/rpc.py
seldon/misc/__init__.py
seldon/misc/item_similarity.py
seldon/misc/most_popular.py
seldon/pipeline/__init__.py
seldon/pipeline/auto_transforms.py
seldon/pipeline/basic_transforms.py
seldon/pipeline/bayes_optimize.py
seldon/pipeline/blender.py
seldon/pipeline/cross_validation.py
seldon/pipeline/pandas_pipelines.py
seldon/pipeline/sklearn_transform.py
seldon/pipeline/tfidf_transform.py
seldon/pipeline/util.py
seldon/rpc/__init__.py
seldon/rpc/seldon_pb2.py
seldon/shell/__init__.py
seldon/shell/attr_schema_utils.py
seldon/shell/cmd_alg.py
seldon/shell/cmd_attr.py
seldon/shell/cmd_client.py
seldon/shell/cmd_db.py
seldon/shell/cmd_import.py
seldon/shell/cmd_memcached.py
seldon/shell/cmd_model.py
seldon/shell/cmdutils.py
seldon/shell/import_actions_utils.py
seldon-2.2.5.dist-info/DESCRIPTION.rst
seldon-2.2.5.dist-info/METADATA
seldon-2.2.5.dist-info/RECORD
seldon-2.2.5.dist-info/WHEEL
seldon-2.2.5.dist-info/dependency_links.txt
seldon-2.2.5.dist-info/metadata.json
seldon-2.2.5.dist-info/top_level.txt
