Metadata-Version: 2.0
Name: seldon
Version: 2.2.5
Summary: Seldon Python Utilities
Home-page: https://github.com/SeldonIO/seldon-server
Author: Clive Cox
Author-email: support@seldon.io
License: Apache 2 License
Platform: UNKNOWN
Requires-Dist: Flask
Requires-Dist: MySQL-python
Requires-Dist: annoy
Requires-Dist: boto
Requires-Dist: cmd2
Requires-Dist: filechunkio
Requires-Dist: gensim
Requires-Dist: kazoo
Requires-Dist: keras
Requires-Dist: luigi
Requires-Dist: numpy
Requires-Dist: pandas (>=0.17)
Requires-Dist: pylibmc
Requires-Dist: scikit-learn (>=0.17)
Requires-Dist: scipy
Requires-Dist: smart-open
Requires-Dist: wabbit-wappa (==3.0.2)
Requires-Dist: xgboost
